MANIFEST.in
README.rst
fnv1a_relay.py
setup.py
fnv1a_relay.egg-info/PKG-INFO
fnv1a_relay.egg-info/SOURCES.txt
fnv1a_relay.egg-info/dependency_links.txt
fnv1a_relay.egg-info/not-zip-safe
fnv1a_relay.egg-info/requires.txt
fnv1a_relay.egg-info/top_level.txt