Metadata-Version: 1.0
Name: fnv1a-relay
Version: 0.1.4
Summary: 
